README.rst
setup.cfg
setup.py
extras/annotate/annotate.py
tssv/__init__.py
tssv/align_pair.py
tssv/cli.py
tssv/sgAlign.c
tssv/sgAlign.h
tssv/sgAlignSSE.c
tssv/sgAlignSSE.h
tssv/sgAlignWrapper.c
tssv/tssv.py
tssv.egg-info/PKG-INFO
tssv.egg-info/SOURCES.txt
tssv.egg-info/dependency_links.txt
tssv.egg-info/entry_points.txt
tssv.egg-info/requires.txt
tssv.egg-info/top_level.txt