Metadata-Version: 1.1
Name: tssv
Version: 1.1.1
Summary: Targeted characterisation of short structural variation.
Home-page: https://git.lumc.nl/j.f.j.laros/tssv
Author: Jeroen F.J. Laros
Author-email: J.F.J.Laros@lumc.nl
License: MIT
Keywords: bioinformatics
Platform: UNKNOWN
Classifier: Intended Audience :: Science/Research
Classifier: Operating System :: OS Independent
Classifier: Programming Language :: Python :: 3
Classifier: Programming Language :: Python :: 3.5
Classifier: Topic :: Scientific/Engineering
